README.md
hello_tea.py
setup.py
Rilley1.egg-info/PKG-INFO
Rilley1.egg-info/SOURCES.txt
Rilley1.egg-info/dependency_links.txt
Rilley1.egg-info/entry_points.txt
Rilley1.egg-info/requires.txt
Rilley1.egg-info/top_level.txt